partis_nwl-0.1.4.data/purelib/partis/nwl/outputs.py
partis_nwl-0.1.4.data/purelib/partis/nwl/query.py
partis_nwl-0.1.4.data/purelib/partis/nwl/__init__.py
partis_nwl-0.1.4.data/purelib/partis/nwl/log.py
partis_nwl-0.1.4.data/purelib/partis/nwl/testing.py
partis_nwl-0.1.4.data/purelib/partis/nwl/utils.py
partis_nwl-0.1.4.data/purelib/partis/nwl/manage/env_modules.py
partis_nwl-0.1.4.data/purelib/partis/nwl/manage/manage.py
partis_nwl-0.1.4.data/purelib/partis/nwl/manage/__init__.py
partis_nwl-0.1.4.data/purelib/partis/nwl/manage/job.py
partis_nwl-0.1.4.data/purelib/partis/nwl/load_tool.py
partis_nwl-0.1.4.data/purelib/partis/nwl/base.py
partis_nwl-0.1.4.data/purelib/partis/nwl/resources.py
partis_nwl-0.1.4.data/purelib/partis/nwl/context.py
partis_nwl-0.1.4.data/purelib/partis/nwl/content_type.py
partis_nwl-0.1.4.data/purelib/partis/nwl/info.py
partis_nwl-0.1.4.data/purelib/partis/nwl/results.py
partis_nwl-0.1.4.data/purelib/partis/nwl/commands/file.py
partis_nwl-0.1.4.data/purelib/partis/nwl/commands/__init__.py
partis_nwl-0.1.4.data/purelib/partis/nwl/commands/process.py
partis_nwl-0.1.4.data/purelib/partis/nwl/commands/base.py
partis_nwl-0.1.4.data/purelib/partis/nwl/commands/dir.py
partis_nwl-0.1.4.data/purelib/partis/nwl/commands/script.py
partis_nwl-0.1.4.data/purelib/partis/nwl/job.py
partis_nwl-0.1.4.data/purelib/partis/nwl/inputs.py
partis_nwl-0.1.4.data/purelib/partis/nwl/runtime.py
partis_nwl-0.1.4.data/purelib/partis/nwl/tool.py
partis_nwl-0.1.4.data/purelib/partis/nwl/allocation.py
partis_nwl-0.1.4.data/purelib/partis/nwl/view/__init__.py
partis_nwl-0.1.4.data/purelib/partis/nwl/view/tool_edit.py
partis_nwl-0.1.4.data/purelib/partis/nwl/view/workflow_edit.py
partis_nwl-0.1.4.data/purelib/partis/nwl/view/tool_results_edit.py
partis_nwl-0.1.4.data/purelib/partis/nwl/view/plugin.py
partis_nwl-0.1.4.data/purelib/partis/nwl/plugin.py
partis_nwl-0.1.4.data/purelib/partis/nwl/tool_pkg/__init__.py
partis_nwl-0.1.4.dist-info/METADATA
partis_nwl-0.1.4.dist-info/LICENSE.txt
partis_nwl-0.1.4.dist-info/top_level.txt
partis_nwl-0.1.4.dist-info/entry_points.txt
partis_nwl-0.1.4.dist-info/WHEEL
partis_nwl-0.1.4.dist-info/RECORD
