Metadata-Version: 2.1
Name: partis-nwl
Version: 0.1.4
Requires-Python: >=3.6.2
Maintainer-email: "Nanohmics Inc." <software.support@nanohmics.com>
Summary: Implementation of Nano Workflow Language (NWL)
License-File: LICENSE.txt
Classifier: Intended Audience :: Science/Research
Classifier: Topic :: System :: Clustering
Classifier: Operating System :: POSIX :: Linux
Classifier: License :: OSI Approved :: BSD License
Classifier: Programming Language :: Python :: 3
Classifier: Development Status :: 4 - Beta
Classifier: Topic :: Scientific/Engineering
Classifier: Programming Language :: Python
Provides-Extra: doc
Requires-Dist: tomli>=1.2.3
Requires-Dist: networkx==2.6.3; python_version < "3.8" and python_version >= "3.7"
Requires-Dist: networkx>=2.8.4; python_version >= "3.8"
Requires-Dist: ruamel.yaml==0.16.5
Requires-Dist: networkx==2.5.1; python_version < "3.7" and python_version >= "3.6"
Requires-Dist: partis-utils[asy,lint]>=0.1.4
Requires-Dist: partis-schema>=0.1.4
Requires-Dist: build>=0.7.0
Requires-Dist: partis-utils[sphinx]>=0.1.4; extra == "doc"
